log/__init__.py
log/main.py
simply_log-0.2.6.dist-info/METADATA
simply_log-0.2.6.dist-info/WHEEL
simply_log-0.2.6.dist-info/top_level.txt
simply_log-0.2.6.dist-info/RECORD
