Metadata-Version: 2.1
Name: simply-log
Version: 0.2.6
Summary: A simple logging.txt library 
Author: cornélius vincent
